chronoeeg/__init__.py
chronoeeg/config.py
chronoeeg/exceptions.py
chronoeeg/logging_config.py
chronoeeg/features/__init__.py
chronoeeg/features/base.py
chronoeeg/features/classical.py
chronoeeg/features/fmm.py
chronoeeg/io/__init__.py
chronoeeg/io/loaders.py
chronoeeg/io/validators.py
chronoeeg/io/validators_advanced.py
chronoeeg/io/wfdb_reader.py
chronoeeg/pipeline/__init__.py
chronoeeg/pipeline/pipeline.py
chronoeeg/preprocessing/__init__.py
chronoeeg/preprocessing/epoching.py
chronoeeg/preprocessing/filters.py
chronoeeg/preprocessing/transforms.py
chronoeeg/quality/__init__.py
chronoeeg/quality/assessors.py
chronoeeg/quality/metrics.py
chronoeeg/utils/__init__.py
chronoeeg/utils/parallel.py
chronoeeg/utils/time.py
chronoeeg/visualization/__init__.py
chronoeeg/visualization/plots.py
chronoeeg-0.1.0.dist-info/licenses/LICENSE
chronoeeg-0.1.0.dist-info/METADATA
chronoeeg-0.1.0.dist-info/WHEEL
chronoeeg-0.1.0.dist-info/top_level.txt
chronoeeg-0.1.0.dist-info/RECORD
