Metadata-Version: 2.4
Name: chronoeeg
Version: 0.1.0
Summary: Advanced multidimensional EEG analysis toolkit with quality assessment and feature extraction
Author-email: Adolfo Santamónica <a.fernandezsantamonica@alumni.maastrichtuniversity.nl>
License: MIT
Project-URL: Homepage, https://github.com/adofersan/chronoeeg
Project-URL: Documentation, https://chronoeeg.readthedocs.io
Project-URL: Repository, https://github.com/adofersan/chronoeeg
Project-URL: Bug Tracker, https://github.com/adofersan/chronoeeg/issues
Keywords: EEG,neuroscience,signal-processing,machine-learning,feature-extraction
Classifier: Development Status :: 3 - Alpha
Classifier: Intended Audience :: Science/Research
Classifier: Intended Audience :: Healthcare Industry
Classifier: License :: OSI Approved :: MIT License
Classifier: Programming Language :: Python :: 3
Classifier: Programming Language :: Python :: 3.8
Classifier: Programming Language :: Python :: 3.9
Classifier: Programming Language :: Python :: 3.10
Classifier: Programming Language :: Python :: 3.11
Classifier: Programming Language :: Python :: 3.12
Classifier: Topic :: Scientific/Engineering :: Medical Science Apps.
Classifier: Topic :: Scientific/Engineering :: Bio-Informatics
Requires-Python: >=3.8
License-File: LICENSE
Requires-Dist: numpy>=1.21.0
Requires-Dist: pandas>=1.3.0
Requires-Dist: scipy>=1.7.0
Requires-Dist: scikit-learn>=1.0.0
Requires-Dist: antropy>=0.1.4
Requires-Dist: neurokit2>=0.2.0
Requires-Dist: joblib>=1.0.0
Requires-Dist: tqdm>=4.62.0
Provides-Extra: dev
Requires-Dist: pytest>=7.0.0; extra == "dev"
Requires-Dist: pytest-cov>=3.0.0; extra == "dev"
Requires-Dist: black>=22.0.0; extra == "dev"
Requires-Dist: flake8>=4.0.0; extra == "dev"
Requires-Dist: mypy>=0.950; extra == "dev"
Requires-Dist: isort>=5.10.0; extra == "dev"
Requires-Dist: pre-commit>=2.17.0; extra == "dev"
Provides-Extra: viz
Requires-Dist: matplotlib>=3.5.0; extra == "viz"
Requires-Dist: seaborn>=0.11.0; extra == "viz"
Requires-Dist: plotly>=5.0.0; extra == "viz"
Provides-Extra: docs
Requires-Dist: sphinx>=4.5.0; extra == "docs"
Requires-Dist: sphinx-rtd-theme>=1.0.0; extra == "docs"
Requires-Dist: sphinx-autodoc-typehints>=1.18.0; extra == "docs"
Dynamic: license-file
